moana/__init__.py
moana/classify/__init__.py
moana/classify/cell_type.py
moana/classify/pca_model.py
moana/classify/plots.py
moana/classify/scmap_cluster.py
moana/classify/simple_cell_type.py
moana/classify/smoothing_model.py
moana/classify/util.py
moana/classify/validate.py
moana/classify/validate_scmap.py
moana/cluster/__init__.py
moana/cluster/cells.py
moana/cluster/plots.py
moana/core/__init__.py
moana/core/cell_ann_matrix.py
moana/core/cell_ann_vector.py
moana/core/exp_matrix.py
moana/core/exp_vector.py
moana/core/matrix.py
moana/core/vector.py
moana/ensembl/__init__.py
moana/ensembl/annotations.py
moana/ensembl/server.py
moana/preprocess/__init__.py
moana/preprocess/pca.py
moana/preprocess/smooth.py
moana/preprocess/util.py
moana/qc/__init__.py
moana/qc/filter.py
moana/qc/plots.py
moana/qc/util.py
moana/tools/__init__.py
moana/tools/dimreduce.py
moana/tools/misc.py
moana/tools/sample.py
moana/util/__init__.py
moana/util/data.py
moana/util/log.py
moana/visualize/__init__.py
moana/visualize/cells.py
moana/visualize/genes.py
moana/visualize/heatmap.py
moana/visualize/util.py
moana-0.1.1.dist-info/METADATA
moana-0.1.1.dist-info/WHEEL
moana-0.1.1.dist-info/entry_points.txt
moana-0.1.1.dist-info/top_level.txt
moana-0.1.1.dist-info/RECORD
