Metadata-Version: 2.1
Name: moana
Version: 0.1.1
Summary: Moana: A robust and scalable cell type classification framework for single-cell RNA-Seq data.
Home-page: https://github.com/yanailab/moana
Author: Florian Wagner
Author-email: florian.wagner@nyu.edu
License: proprietary
Platform: UNKNOWN
Classifier: Development Status :: 3 - Alpha
Classifier: Intended Audience :: Developers
Classifier: Intended Audience :: Science/Research
Classifier: Topic :: Scientific/Engineering :: Bio-Informatics
Classifier: License :: Other/Proprietary License
Classifier: Programming Language :: Python :: 3.5
Classifier: Programming Language :: Python :: 3.6
Classifier: Programming Language :: Python :: 3.7
Requires-Dist: scikit-learn (<1,>=0.19.1)
Requires-Dist: pandas (<1,>=0.21.1)
Requires-Dist: plotly (<3,>=2.0.0)
Requires-Dist: scipy (<2,>=1)
Requires-Dist: numpy (<2,>=1)
Provides-Extra: docs
Requires-Dist: sphinx; extra == 'docs'
Requires-Dist: sphinx-rtd-theme; extra == 'docs'
Requires-Dist: sphinx-argparse; extra == 'docs'
Requires-Dist: mock; extra == 'docs'
Provides-Extra: tests
Requires-Dist: pytest (<4,>=3); extra == 'tests'
Requires-Dist: pytest-cov (<3,>=2.2.1); extra == 'tests'
